<?xml version="1.0" encoding="utf-8" ?><dwsync><file name="code_generator.phps" server="ftp.travailetculture.com" local="3548016576" remote="318763443942494532" Dst="-1" /><file name="contents.html" server="ftp.travailetculture.com" local="3548016576" remote="318763443942494532" Dst="-1" /><file name="contentsutf8.html" server="ftp.travailetculture.com" local="3548016576" remote="318763443942494532" Dst="-1" /><file name="DKIM.phps" server="ftp.travailetculture.com" local="3548016576" remote="318763443942494532" Dst="-1" /><file name="exceptions.phps" server="ftp.travailetculture.com" local="3548016576" remote="318763443942494532" Dst="-1" /><file name="gmail.phps" server="ftp.travailetculture.com" local="3548016576" remote="318763443942494532" Dst="-1" /><file name="gmail_xoauth.phps" server="ftp.travailetculture.com" local="3548016576" remote="318763443942494532" Dst="-1" /><file name="mail.phps" server="ftp.travailetculture.com" local="3548016576" remote="318763443942494532" Dst="-1" /><file name="mailing_list.phps" server="ftp.travailetculture.com" local="3548016576" remote="318763443942494532" Dst="-1" /><file name="index.html" server="ftp.travailetculture.com" local="3548016576" remote="318763443942494532" Dst="-1" /><file name="pop_before_smtp.phps" server="ftp.travailetculture.com" local="3548016576" remote="318763443942494532" Dst="-1" /><file name="send_file_upload.phps" server="ftp.travailetculture.com" local="3548016576" remote="318763443942494532" Dst="-1" /><file name="send_multiple_file_upload.phps" server="ftp.travailetculture.com" local="3548016576" remote="318763443942494532" Dst="-1" /><file name="sendmail.phps" server="ftp.travailetculture.com" local="3548016576" remote="318763443942494532" Dst="-1" /><file name="signed-mail.phps" server="ftp.travailetculture.com" local="3548016576" remote="318763443942494532" Dst="-1" /><file name="smtp.phps" server="ftp.travailetculture.com" local="3548016576" remote="318763443942494532" Dst="-1" /><file name="smtp_check.phps" server="ftp.travailetculture.com" local="3548016576" remote="318763443942494532" Dst="-1" /><file name="smtp_no_auth.phps" server="ftp.travailetculture.com" local="3548016576" remote="318763443942494532" Dst="-1" /><file name="ssl_options.phps" server="ftp.travailetculture.com" local="3548016576" remote="318763443942494532" Dst="-1" /></dwsync>